Library/__init__.py
Library/main.py
Library/utils.py
tests/__init__.py
tests/test_main.py
GaonSD-0.1.dist-info/LICENSE
GaonSD-0.1.dist-info/METADATA
GaonSD-0.1.dist-info/WHEEL
GaonSD-0.1.dist-info/top_level.txt
GaonSD-0.1.dist-info/RECORD
